lookmlint/__init__.py
lookmlint/cli.py
lookmlint/lookml.py
lookmlint/lookmlint.py
lookmlint-1.0.3.dist-info/LICENSE
lookmlint-1.0.3.dist-info/METADATA
lookmlint-1.0.3.dist-info/WHEEL
lookmlint-1.0.3.dist-info/entry_points.txt
lookmlint-1.0.3.dist-info/top_level.txt
lookmlint-1.0.3.dist-info/RECORD
