Metadata-Version: 2.1
Name: lookmlint
Version: 1.0.3
Summary: Linter for LookML
Home-page: https://github.com/WarbyParker/lookmlint
Author: Ryan Tuck
Author-email: ryan.tuck@warbyparker.com
License: UNKNOWN
Platform: UNKNOWN
Requires-Dist: attrs
Requires-Dist: click
Requires-Dist: lkml (==0.2.2)
Requires-Dist: pyyaml
